{"is_source_file": true, "format": "TypeScript", "description": "A source file defining configuration for static site rendering in a frontend project, specifically setting prerendering to true.", "external_files": [], "external_methods": [], "published": ["prerender"], "classes": [], "methods": [], "calls": [], "search-terms": ["prerender", "static site", "frontend route configuration"], "state": 2, "file_id": 4, "knowledge_revision": 21, "git_revision": "7338807742069f79f5f3f9bd6dd15f473700593e", "ctags": [{"_type": "tag", "name": "prerender", "path": "/home/kavia/workspace/code-generation/simple-notes-manager-173296-173334/notes_frontend/src/routes/+page.ts", "pattern": "/^export const prerender = true;$/", "language": "TypeScript", "kind": "constant"}], "hash": "a20aecd382022d6c9654ef9b5a27c969", "format-version": 4, "code-base-name": "notes_frontend", "filename": "notes_frontend/src/routes/+page.ts", "revision_history": [{"21": "7338807742069f79f5f3f9bd6dd15f473700593e"}]}